{"name":"AsyncMe","tagline":"Chargement asynchrone de vos médias","body":"Async Me\r\n======\r\n**Async Me** est un plug-in JS permettant le lazy loading d'images et d'iframe Youtube.\r\n\r\n```html\r\n<img src=\"spinner.png\" data-src=\"votre_image\" class=\"async-me\" />\r\n```\r\n## Fonctionnement\r\n### Paramètres\r\n\r\n| Attribut       |     Format       |   Default   | Obligatoire |  Description                                              |\r\n| ---:           |           ---:   |      :---:  |     :---:   |                                                      ---: |\r\n| data-src       |    *string*      |      -      |      Oui    | Chemin du média à charger                                 |\r\n| data-time-out  |    *int*         |     null    |      Non    | Délai d'activation du chargment asynchrone                |\r\n| data-effect    |    *string*      |    fadeIn   |      Non    | Effet d'animation (*fadeIn, fadeOut, slideDown, slideUp*) |\r\n| data-speed     |    *int, string* |    fast     |      Non    | Vitesse d'éxécution de l'animation                        |\r\n\r\n### Avec l'attribut data\r\n```html\r\n<img class=\"async-me\" src=\"spinner.png\" data-src=\"votre_image\" data-time-out=\"800\" data-effect=\"fadeOut\" data-speed=\"900\" />\r\n```\r\n### En jQuery\r\n```javascript\r\n$('votre_element').asyncMe({\r\n  speed: 900\r\n  timeOut: 800\r\n  effect: 'fadeOut',\r\n});\r\n```\r\n## Version\r\n* Version 1.0\r\n\r\n## Contact\r\n#### Developpeur\r\n* Site Web: [devtalk.fr](http://devtalk.fr)\r\n* e-mail: contact@devtalk.fr\r\n* Twitter: [@fj0ker](https://twitter.com/fj0ker)\r\n","google":"","note":"Don't delete this file! It's used internally to help with page regeneration."}